    {
    "layoutVersion": 1,
    "keyConfig": [
        {
            "type": "Rect",
            "x": 0,
            "y": 0,
            "width": 250,
            "height": 250,
            "onPressAction": [
                { "condition": "NUMPAD", "action":"INPUT:&1" },
                { "condition": "CAPS", "action":"INPUT:&Т" },
                { "action":"INPUT:&т" }
            ],
            "roll": -22.5,
            "onSwipeActions": [
                null,
                null,
                [
                    { "condition": "CAPS", "action":"INPUT:&Ч" },
                    { "action":"INPUT:&ч" }
                ],
                { "action":"CONTINUE" },
                { "action":"CONTINUE" },
                null,
                null,
                null
            ]
        },
        {
            "type": "Rect",
            "x": 250,
            "y": 0,
            "width": 250,
            "height": 250,
            "roll": -22.5,
            "onPressAction": [
                { "condition": "NUMPAD", "action":"INPUT:&2" },
                { "condition": "CAPS", "action":"INPUT:&А" },
                { "action":"INPUT:&а" }
            ],
            "onSwipeActions": [
                null,
                null,
                null,
                null,
                [
                    { "condition": "CAPS", "action":"INPUT:&Д" },
                    { "action":"INPUT:&д" }
                ],
                null,
                null,
                [
                    { "condition": "CAPS", "action":"INPUT:&Ю" },
                    { "action":"INPUT:&ю" }
                ]
            ]
        },
        {
            "type": "Rect",
            "x": 500,
            "y": 0,
            "width": 250,
            "height": 250,
            "roll": -22.5,
            "onPressAction": [
                { "condition": "NUMPAD", "action":"INPUT:&3" },
                { "condition": "CAPS", "action":"INPUT:&И" },
                { "action":"INPUT:&и" }
            ],
            "onSwipeActions": [
                null,
                [
                    { "condition": "CAPS", "action":"INPUT:&Й" },
                    { "action":"INPUT:&й" }
                ],
                null,
                [
                    { "condition": "CAPS", "action":"INPUT:&Я" },
                    { "action":"INPUT:&я" }
                ],
                [
                    { "condition": "CAPS", "action":"INPUT:&П" },
                    { "action":"INPUT:&п" }
                ],
                [
                    { "condition": "CAPS", "action":"INPUT:&Ь" },
                    { "action":"INPUT:&ь" }
                ],
                null,
                null
            ]
        },
        {
            "type": "Rect",
            "x": 750,
            "y": 0,
            "width": 250,
            "height": 250,
            "roll": -22.5,
            "onPressAction": [
                { "condition": "NUMPAD", "action":"INPUT:&0" },
                { "condition": "CAPS", "action":"INPUT:&Н" },
                { "action":"INPUT:&н" }
            ],
            "onSwipeActions": [
                null,
                null,
                null,
                null,
                [
                    { "condition": "CAPS", "action":"INPUT:&Ъ" },
                    { "action":"INPUT:&ъ" }
                ],
                [
                    { "condition": "CAPS", "action":"INPUT:&Б" },
                    { "action":"INPUT:&б" }
                ],
                [
                    { "condition": "CAPS", "action":"INPUT:&Щ" },
                    { "action":"INPUT:&щ" }
                ],
                null
            ]
        },
        {
            "type": "Rect",
            "x": 0,
            "y": 250,
            "width": 250,
            "height": 250,
            "roll": -22.5,
            "onPressAction": [
                { "condition": "NUMPAD", "action":"INPUT:&4" },
                { "condition": "CAPS", "action":"INPUT:&В" },
                { "action":"INPUT:&в" }
            ],
            "onSwipeActions": [
                null,
                null,
                [
                    { "condition": "CAPS", "action":"INPUT:&Ц" },
                    { "action":"INPUT:&ц" }
                ],
                null,
                null,
                null,
                null,
                null
            ]
        },
        {
            "type": "Rect",
            "x": 250,
            "y": 250,
            "width": 250,
            "height": 250,
            "roll": -22.5,
            "onPressAction": [
                { "condition": "NUMPAD", "action":"INPUT:&5" },
                { "condition": "CAPS", "action":"INPUT:&О" },
                { "action":"INPUT:&о" }
            ],
            "onSwipeActions": [
                null,
                null,
                null,
                [
                    { "condition": "CAPS", "action":"INPUT:&Ш" },
                    { "action":"INPUT:&ш" }
                ],
                null,
                null,
                null,
                [
                    { "condition": "CAPS", "action":"INPUT:&Ы" },
                    { "action":"INPUT:&ы" }
                ]
            ]
        },
        {
            "type": "Rect",
            "x": 500,
            "y": 250,
            "width": 250,
            "height": 250,
            "roll": -22.5,
            "onPressAction": [
                { "condition": "NUMPAD", "action":"INPUT:&6" },
                { "condition": "CAPS", "action":"INPUT:&Е" },
                { "action":"INPUT:&е" }
            ],
            "onSwipeActions": [
                null,
                [
                    { "condition": "CAPS", "action":"INPUT:&У" },
                    { "action":"INPUT:&у" }
                ],
                null,
                null,
                null,
                [
                    { "condition": "CAPS", "action":"INPUT:&Г" },
                    { "action":"INPUT:&г" }
                ],
                null,
                [
                    { "condition": "CAPS", "action":"INPUT:&Ё" },
                    { "action":"INPUT:&ё" }
                ]
            ]
        },
        {
            "type": "Rect",
            "x": 750,
            "y": 250,
            "width": 250,
            "height": 250,
            "roll": -22.5,
            "onPressAction": [
                { "condition": "CAPS", "action":"INPUT:&Л" },
                { "action":"INPUT:&л" }
            ],
            "onSwipeActions": [
                { "action":"CAPS_TOGGLE", "icon": "#!CAPS_UP" },
                null,
                { "action":"CYCLE_LAYOUT" },
                null,
                null,
                [
                    { "condition": "CAPS", "action":"INPUT:&Э" },
                    { "action":"INPUT:&э" }
                ],
                null,
                [
                    { "condition": "CAPS", "action":"INPUT:&Ж" },
                    { "action":"INPUT:&ж" }
                ]
            ]
        },
        {
            "type": "Rect",
            "x": 0,
            "y": 500,
            "width": 250,
            "height": 250,
            "roll": -22.5,
            "onPressAction": [
                { "condition": "NUMPAD", "action":"INPUT:&7" },
                { "condition": "CAPS", "action":"INPUT:&К" },
                { "action":"INPUT:&к" }
            ],
            "onSwipeActions": [
                null,
                null,
                null,
                null,
                null,
                null,
                null,
                null
            ]
        },
        {
            "type": "Rect",
            "x": 250,
            "y": 500,
            "width": 250,
            "height": 250,
            "roll": -22.5,
            "onPressAction": [
                { "condition": "NUMPAD", "action":"INPUT:&8" },
                { "condition": "CAPS", "action":"INPUT:&Р" },
                { "action":"INPUT:&р" }
            ],
            "onSwipeActions": [
                null,
                null,
                null,
                null,
                null,
                null,
                null,
                [
                    { "condition": "CAPS", "action":"INPUT:&З" },
                    { "action":"INPUT:&з" }
                ]
            ]
        },
        {
            "type": "Rect",
            "x": 500,
            "y": 500,
            "width": 250,
            "height": 250,
            "roll": -22.5,
            "onPressAction": [
                { "condition": "NUMPAD", "action":"INPUT:&9" },
                { "condition": "CAPS", "action":"INPUT:&С" },
                { "action":"INPUT:&с" }
            ],
            "onSwipeActions": [
                [
                    { "condition": "CAPS", "action":"INPUT:&Ф" },
                    { "action":"INPUT:&ф" }
                ],
                [
                    { "condition": "CAPS", "action":"INPUT:&Х" },
                    { "action":"INPUT:&х" }
                ],
                null,
                null,
                null,
                null,
                null,
                null
            ]
        },
        {
            "type": "Rect",
            "x": 750,
            "y": 500,
            "width": 250,
            "height": 250,
            "roll": -22.5,
            "onPressAction": [
                { "condition": "CAPS", "action":"INPUT:&М" },
                { "action":"INPUT:&м" }
            ],
            "hideRadials": true,
            "onSwipeActions": [
                "Q",
                "R",
                "N",
                "J"
            ]
        },
        {
            "type": "Rect",
            "x": 0,
            "y": 750,
            "isAccented": true,
            "isAltColor": true,
            "width": 130,
            "height": 180,
            "onPressAction": { "action":"CAPS_TOGGLE", "icon": "#!CAPS_UP" },
            "hideRadials": true,
            "onSwipeActions": [
                "Q",
                "R"
            ]
        },
        {
            "type": "Rect",
            "x": 130,
            "y": 750,
            "isAccented": true,
            "isAltColor": false,
            "width": 520,
            "height": 180,
            "onPressAction": { "action":"INPUT:@KEYCODE_SPACE", "icon": "#!SPACE" },
            "hideRadials": true,
            "onSwipeActions": [
            ]
        },
        {
            "type": "Rect",
            "x": 650,
            "y": 750,
            "isAccented": true,
            "isAltColor": true,
            "width": 150,
            "height": 180,
            "onPressAction": { "action":"INPUT:@KEYCODE_BACKSPACE", "icon": "#!BACKSPACE" },
            "hideRadials": true,
            "onSwipeActions": [
                "Q",
                "R"
            ]
        },
        {
            "type": "Rect",
            "x": 800,
            "y": 750,
            "isAccented": true,
            "isAltColor": false,
            "width": 200,
            "height": 180,
            "onPressAction": { "action":"INPUT:@KEYCODE_ENTER", "icon": "#!RETURN" },
            "hideRadials": true,
            "onSwipeActions": [
                "Q",
                "R"
            ]
        }
    ]
}